caen_felib/__init__.py
caen_felib/_cache.py
caen_felib/_utils.py
caen_felib/device.py
caen_felib/dig1_types.py
caen_felib/dig2_types.py
caen_felib/error.py
caen_felib/lib.py
caen_felib/py.typed
caen_felib-1.4.0.dist-info/licenses/COPYING
caen_felib-1.4.0.dist-info/licenses/COPYING.LESSER
caen_felib-1.4.0.dist-info/METADATA
caen_felib-1.4.0.dist-info/WHEEL
caen_felib-1.4.0.dist-info/top_level.txt
caen_felib-1.4.0.dist-info/RECORD
