Metadata-Version: 2.4
Name: caen_felib
Version: 1.4.0
Summary: Official Python binding for the CAEN FELib.
Author: Giovanni Cerretani, Daniele Ninci
Project-URL: Homepage, https://www.caen.it
Project-URL: Documentation, https://www.caen.it/products/caen-felib-library/
Project-URL: Support, https://www.caen.it/mycaen/support/
Project-URL: Source, https://github.com/caenspa/py-caen-felib
Project-URL: Changelog, https://github.com/caenspa/py-caen-felib/blob/master/PYCHANGELOG
Classifier: Development Status :: 5 - Production/Stable
Classifier: Intended Audience :: Science/Research
Classifier: License :: OSI Approved :: GNU Lesser General Public License v3 or later (LGPLv3+)
Classifier: Natural Language :: English
Classifier: Operating System :: OS Independent
Classifier: Programming Language :: Python :: 3
Classifier: Programming Language :: Python :: 3.9
Classifier: Programming Language :: Python :: 3.10
Classifier: Programming Language :: Python :: 3.11
Classifier: Programming Language :: Python :: 3.12
Classifier: Programming Language :: Python :: 3.13
Classifier: Topic :: Scientific/Engineering :: Physics
Classifier: Typing :: Typed
Requires-Python: >=3.9
License-File: COPYING
License-File: COPYING.LESSER
Requires-Dist: numpy>=2.0
Requires-Dist: typing-extensions>=4.0
Dynamic: license-file
